fastotp/__init__.py
fastotp/client.py
fastotp/exceptions.py
fastotp/utils.py
tests/__init__.py
tests/test_client.py
fastotp_sdk-0.1.0.dist-info/LICENSE
fastotp_sdk-0.1.0.dist-info/METADATA
fastotp_sdk-0.1.0.dist-info/WHEEL
fastotp_sdk-0.1.0.dist-info/top_level.txt
fastotp_sdk-0.1.0.dist-info/RECORD
