Metadata-Version: 2.1
Name: fastotp_sdk
Version: 0.1.0
Summary: A Python SDK for FastOTP API
Home-page: https://github.com/ipeluwa/fastotp_sdk
Author: Oluwapeluwa Ibrahim
Author-email: ipeluwa@gmail.com
Classifier: Programming Language :: Python :: 3
Classifier: License :: OSI Approved :: MIT License
Classifier: Operating System :: OS Independent
Requires-Python: >=3.6
License-File: LICENSE
Requires-Dist: httpx
